orangecontrib/tomwer/__init__.py
orangecontrib/tomwer/state_summary.py
orangecontrib/tomwer/orange/__init__.py
orangecontrib/tomwer/orange/managedprocess.py
orangecontrib/tomwer/orange/settings.py
orangecontrib/tomwer/tests/TestAcquisition.py
orangecontrib/tomwer/tests/__init__.py
orangecontrib/tomwer/tutorials/EBS_tomo_listener.ows
orangecontrib/tomwer/tutorials/__init__.py
orangecontrib/tomwer/tutorials/append_raw_darks_and_flats_frames_to_NXtomos.ows
orangecontrib/tomwer/tutorials/cast_volume.ows
orangecontrib/tomwer/tutorials/copy_reduced_darks_and_flats_meth1.ows
orangecontrib/tomwer/tutorials/copy_reduced_darks_and_flats_meth2.ows
orangecontrib/tomwer/tutorials/default_cor_search.ows
orangecontrib/tomwer/tutorials/drac_publication.ows
orangecontrib/tomwer/tutorials/hello_world_python_script.ows
orangecontrib/tomwer/tutorials/simple_slice_reconstruction.ows
orangecontrib/tomwer/tutorials/simple_slice_reconstruction_on_slurm.ows
orangecontrib/tomwer/tutorials/simple_volume_local_reconstruction.ows
orangecontrib/tomwer/tutorials/simple_volume_to_slurm_reconstruction.ows
orangecontrib/tomwer/tutorials/using_saaxis_to_find_cor.ows
orangecontrib/tomwer/tutorials/volume_casting_on_slurm.ows
orangecontrib/tomwer/tutorials/id16b/ID16b_full_volume.ows
orangecontrib/tomwer/tutorials/id16b/ID16b_insitu.ows
orangecontrib/tomwer/tutorials/id16b/ID16b_normalization.ows
orangecontrib/tomwer/tutorials/id16b/__init__.py
orangecontrib/tomwer/widgets/__init__.py
orangecontrib/tomwer/widgets/utils.py
orangecontrib/tomwer/widgets/cluster/FutureSupervisorOW.py
orangecontrib/tomwer/widgets/cluster/SlurmClusterOW.py
orangecontrib/tomwer/widgets/cluster/__init__.py
orangecontrib/tomwer/widgets/cluster/icons/slurm.png
orangecontrib/tomwer/widgets/cluster/icons/slurm.svg
orangecontrib/tomwer/widgets/cluster/icons/slurmobserver.png
orangecontrib/tomwer/widgets/cluster/icons/slurmobserver.svg
orangecontrib/tomwer/widgets/cluster/tests/__init__.py
tomwer-1.6.13.dist-info/licenses/LICENSE
tomwer-1.6.13.dist-info/METADATA
tomwer-1.6.13.dist-info/WHEEL
tomwer-1.6.13.dist-info/entry_points.txt
tomwer-1.6.13.dist-info/top_level.txt
tomwer-1.6.13.dist-info/RECORD
