Metadata-Version: 2.4
Name: tomwer
Version: 1.6.13
Summary: Tomography workflow tools
Author-email: Henri Payno <henri.payno@esrf.fr>, Pierre Paleo <pierre.paleo@esrf.fr>, Pierre-Olivier Autran <pierre-olivier.autran@esrf.fr>, Jérôme Lesaint <jerome.lesaint@esrf.fr>, Alessandro Mirone <mirone@esrf.fr>
License: MIT
Project-URL: Homepage, https://gitlab.esrf.fr/tomotools/tomwer
Project-URL: Documentation, https://tomotools.gitlab-pages.esrf.fr/tomwer/
Project-URL: Repository, https://gitlab.esrf.fr/tomotools/tomwer
Project-URL: Issues, https://gitlab.esrf.fr/tomotools/tomwer/-/issues
Project-URL: Changelog, https://gitlab.esrf.fr/tomotools/tomwer/-/blob/main/CHANGELOG.rst?ref_type=heads
Keywords: orange3 add-on,ewoks
Classifier: Intended Audience :: Education
Classifier: Intended Audience :: Science/Research
Classifier: License :: OSI Approved :: MIT License
Classifier: Programming Language :: Python :: 3
Classifier: Environment :: Console
Classifier: Environment :: X11 Applications :: Qt
Classifier: Operating System :: POSIX
Classifier: Natural Language :: English
Classifier: Topic :: Scientific/Engineering :: Physics
Classifier: Topic :: Software Development :: Libraries :: Python Modules
Requires-Python: >=3.10
License-File: LICENSE
Requires-Dist: numpy
Requires-Dist: setuptools
Requires-Dist: psutil
Requires-Dist: silx[full]>=2.1.1
Requires-Dist: tomoscan>=2.2.0a6
Requires-Dist: nxtomo>2.0.0dev2
Requires-Dist: nxtomomill>=2.0.0dev0
Requires-Dist: processview>=1.5.0
Requires-Dist: ewoks>=0.1.1
Requires-Dist: ewokscore<2.0,>=1.5
Requires-Dist: sluurp>=0.4.1
Requires-Dist: packaging
Requires-Dist: pint
Requires-Dist: tqdm
Requires-Dist: eval_type_backport; python_version < "3.10"
Provides-Extra: full-base
Requires-Dist: orange-canvas-core; extra == "full-base"
Requires-Dist: orange-widget-base; extra == "full-base"
Requires-Dist: ewoks[orange]>=0.1.1; extra == "full-base"
Requires-Dist: ewoksorange<2.0,>=0.7.0rc0; extra == "full-base"
Requires-Dist: fabio; extra == "full-base"
Requires-Dist: h5py>=3; extra == "full-base"
Requires-Dist: lxml; extra == "full-base"
Requires-Dist: werkzeug; extra == "full-base"
Requires-Dist: json-rpc; extra == "full-base"
Requires-Dist: scipy; extra == "full-base"
Requires-Dist: Pillow; extra == "full-base"
Requires-Dist: resource; extra == "full-base"
Requires-Dist: tifffile; extra == "full-base"
Requires-Dist: hdf5plugin; extra == "full-base"
Requires-Dist: pyicat_plus; extra == "full-base"
Requires-Dist: ewoksnotify[full]<0.2; extra == "full-base"
Requires-Dist: pyicat_plus; extra == "full-base"
Requires-Dist: rsyncmanager; extra == "full-base"
Requires-Dist: blissdata; extra == "full-base"
Provides-Extra: full-no-cuda
Requires-Dist: tomwer[full_base]; extra == "full-no-cuda"
Requires-Dist: nabu>=2024.2.0; extra == "full-no-cuda"
Provides-Extra: full
Requires-Dist: tomwer[full_base]; extra == "full"
Requires-Dist: nabu[full]>=2024.2.0; extra == "full"
Requires-Dist: pycuda<2024.1.1; extra == "full"
Requires-Dist: scikit-cuda; extra == "full"
Provides-Extra: doc
Requires-Dist: tomwer[full_no_cuda]; extra == "doc"
Requires-Dist: Sphinx>=4.0.0; extra == "doc"
Requires-Dist: nbsphinx; extra == "doc"
Requires-Dist: pandoc; extra == "doc"
Requires-Dist: jupyterlab; extra == "doc"
Requires-Dist: pydata_sphinx_theme; extra == "doc"
Requires-Dist: sphinx-design; extra == "doc"
Requires-Dist: sphinx-autodoc-typehints; extra == "doc"
Requires-Dist: sphinxcontrib-programoutput; extra == "doc"
Requires-Dist: sphinxcontrib-youtube; extra == "doc"
Requires-Dist: myst-parser; extra == "doc"
Provides-Extra: dev-spec
Requires-Dist: black; extra == "dev-spec"
Requires-Dist: flake8; extra == "dev-spec"
Requires-Dist: timeout-decorator; extra == "dev-spec"
Requires-Dist: pyopencl; extra == "dev-spec"
Provides-Extra: dev
Requires-Dist: tomwer[full]; extra == "dev"
Requires-Dist: tomwer[dev_spec]; extra == "dev"
Provides-Extra: dev-no-cuda
Requires-Dist: tomwer[full_no_cuda]; extra == "dev-no-cuda"
Requires-Dist: tomwer[dev_spec]; extra == "dev-no-cuda"
Provides-Extra: test
Requires-Dist: tomwer[full_no_cuda]; extra == "test"
Requires-Dist: pytest-asyncio; extra == "test"
Requires-Dist: tomoscan[test]>=2.2.0a6; extra == "test"
Dynamic: license-file
